labone/__init__.py
labone/_version.py
labone-4.0.0.dist-info/METADATA
labone-4.0.0.dist-info/WHEEL
labone-4.0.0.dist-info/licenses/LICENSE
labone-4.0.0.dist-info/RECORD
